corsheaders/__init__.py
corsheaders/defaults.py
corsheaders/middleware.py
corsheaders/models.py
corsheaders/signals.py
corsheaders/tests.py
corsheaders/migrations/0001_initial.py
corsheaders/migrations/__init__.py
django_cors_middleware-1.4.0.dist-info/LICENSE.txt
django_cors_middleware-1.4.0.dist-info/METADATA
django_cors_middleware-1.4.0.dist-info/WHEEL
django_cors_middleware-1.4.0.dist-info/top_level.txt
django_cors_middleware-1.4.0.dist-info/RECORD
