Metadata-Version: 1.1
Name: django-cors-middleware
Version: 1.4.0
Summary: django-cors-middleware is a Django application for handling the server headers required for Cross-Origin Resource Sharing (CORS). Fork of django-cors-headers.
Home-page: https://github.com/zestedesavoir/django-cors-middleware
Author: Zeste de Savoir
Author-email: dev@gustavi.net
License: MIT License
Keywords: django cors middleware rest api
Platform: any
Classifier: Development Status :: 5 - Production/Stable
Classifier: Environment :: Web Environment
Classifier: Framework :: Django
Classifier: Intended Audience :: Developers
Classifier: License :: OSI Approved :: MIT License
Classifier: Operating System :: OS Independent
Classifier: Programming Language :: Python
Classifier: Programming Language :: Python :: 2
Classifier: Programming Language :: Python :: 2.7
Classifier: Programming Language :: Python :: 3
Classifier: Programming Language :: Python :: 3.3
Classifier: Programming Language :: Python :: 3.4
Classifier: Programming Language :: Python :: 3.5
Classifier: Programming Language :: Python :: 3.6
Classifier: Programming Language :: Python :: 3.7
Classifier: Topic :: Software Development :: Libraries :: Application Frameworks
Classifier: Topic :: Software Development :: Libraries :: Python Modules
